pyrlint/__init__.py
pyrlint/tokenizer.py
pyrlint/tools/colorize.py
pyrlint-0.1.0a0.dist-info/licenses/LICENSE
pyrlint-0.1.0a0.dist-info/METADATA
pyrlint-0.1.0a0.dist-info/WHEEL
pyrlint-0.1.0a0.dist-info/entry_points.txt
pyrlint-0.1.0a0.dist-info/top_level.txt
pyrlint-0.1.0a0.dist-info/RECORD
