Metadata-Version: 2.4
Name: pyrlint
Version: 0.1.0a0
Summary: Python implementation of lint tools for R language.
Author-email: hxt-tg <hxt.taoge@gmail.com>
Maintainer-email: hxt-tg <hxt.taoge@gmail.com>
Requires-Python: >=3.8
License-File: LICENSE
Requires-Dist: importlib-metadata>=3.6.0; python_version < "3.12"
Dynamic: license-file
